Workbook

Sheet UNH
A1: Date | B1: Open | C1: High | D1: Low | E1: Close | F1: Adj Close | G1: Volume | H1: RET
A3: 45597 | B3: 565.12 | C3: 630.73 | D3: 554.4 | E3: 592.23 | F3: 592.23 | G3: 39257900 | H3: =F3/F4-1 -> 0.049123118
A4: 45566 | B4: 585 | C4: 608.63 | D4: 543 | E4: 564.5 | F4: 564.5 | G4: 74141000 | H4: =F4/F5-1 -> -0.031084259
A5: 45536 | B5: 592.52 | C5: 607.94 | D5: 566 | E5: 584.68 | F5: 582.61 | G5: 60936400 | H5: =F5/F6-1 -> -0.009351992
A6: 45505 | B6: 577.2 | C6: 593.26 | D6: 557.03 | E6: 590.2 | F6: 588.11 | G6: 60428700 | H6: =F6/F7-1 -> 0.024367728
A7: 45474 | B7: 506.75 | C7: 581.5 | D7: 484.5 | E7: 576.16 | F7: 574.12 | G7: 95463400 | H7: =F7/F8-1 -> 0.13615135
A8: 45444 | B8: 494.13 | C8: 509.4 | D8: 478.11 | E8: 509.26 | F8: 505.32 | G8: 89757500 | H8: =F8/F9-1 -> 0.028055256
A9: 45413 | B9: 479.26 | C9: 528.16 | D9: 473.27 | E9: 495.37 | F9: 491.53 | G9: 72644700 | H9: =F9/F10-1 -> 0.024127513
A10: 45383 | B10: 494.47 | C10: 507.3 | D10: 436.38 | E10: 483.7 | F10: 479.95 | G10: 120751600 | H10: =F10/F11-1 -> -0.018386714
A11: 45352 | B11: 489.42 | C11: 496.2 | D11: 468.19 | E11: 494.7 | F11: 488.94 | G11: 82467300 | H11: =F11/F12-1 -> 0.0022342933
A12: 45323 | B12: 508.83 | C12: 532.81 | D12: 484.39 | E12: 493.6 | F12: 487.85 | G12: 70448600 | H12: =F12/F13-1 -> -0.035450196
A13: 45292 | B13: 526.84 | C13: 549 | D13: 479 | E13: 511.74 | F13: 505.78 | G13: 97040500 | H13: =F13/F14-1 -> -0.02466398
A14: 45261 | B14: 550.42 | C14: 554.7 | D14: 515.87 | E14: 526.47 | F14: 518.57 | G14: 61590800 | H14: =F14/F15-1 -> -0.047936403
... A61: 43831 | B61: 293.98 | C61: 302.54 | D61: 271.18 | E61: 272.45 | F61: 254.12 | G61: 84374200 | H61: =F61/F62-1 -> -0.06966868
A62: 43800 | B62: 281.78 | C62: 300 | D62: 273.85 | E62: 293.98 | F62: 273.15 | G62: 60550900

Sheet SPY
A2: Date | B2: Open | C2: High | D2: Low | E2: Close | F2: Adj Close | G2: Volume | H2: RET
A3: 45597 | B3: 571.32 | C3: 576.74 | D3: 567.89 | E3: 576.7 | F3: 576.7 | G3: 122943700 | H3: =[1]spy!F1/[1]spy!F2-1 -> 0.01417417
A4: 45566 | B4: 573.4 | C4: 586.12 | D4: 565.27 | E4: 568.64 | F4: 568.64 | G4: 976068800 | H4: =[1]spy!F2/[1]spy!F3-1 -> -0.0058915054
A5: 45536 | B5: 558.35 | C5: 574.71 | D5: 539.44 | E5: 573.76 | F5: 572.01 | G5: 1045061400 | H5: =[1]spy!F3/[1]spy!F4-1 -> 0.017883835
A6: 45505 | B6: 552.57 | C6: 564.2 | D6: 510.27 | E6: 563.68 | F6: 561.96 | G6: 1244599000 | H6: =[1]spy!F4/[1]spy!F5-1 -> 0.023364231
A7: 45474 | B7: 545.63 | C7: 565.16 | D7: 537.45 | E7: 550.81 | F7: 549.13 | G7: 1038465500 | H7: =[1]spy!F5/[1]spy!F6-1 -> 0.015384331
A8: 45444 | B8: 529.02 | C8: 550.28 | D8: 522.6 | E8: 544.22 | F8: 540.81 | G8: 888923200 | H8: =[1]spy!F6/[1]spy!F7-1 -> 0.031942298
A9: 45413 | B9: 501.38 | C9: 533.07 | D9: 499.55 | E9: 527.37 | F9: 524.07 | G9: 1153264400 | H9: =[1]spy!F7/[1]spy!F8-1 -> 0.050577339
A10: 45383 | B10: 523.83 | C10: 524.38 | D10: 493.86 | E10: 501.98 | F10: 498.84 | G10: 1592974000 | H10: =[1]spy!F8/[1]spy!F9-1 -> -0.037322938
A11: 45352 | B11: 508.98 | C11: 524.61 | D11: 504.91 | E11: 523.07 | F11: 518.18 | G11: 1473246900 | H11: =[1]spy!F9/[1]spy!F10-1 -> 0.029503507
A12: 45323 | B12: 484.63 | C12: 510.13 | D12: 483.8 | E12: 508.08 | F12: 503.33 | G12: 1393465400 | H12: =[1]spy!F10/[1]spy!F11-1 -> 0.052177185
A13: 45292 | B13: 472.16 | C13: 491.62 | D13: 466.43 | E13: 482.88 | F13: 478.37 | G13: 1700630800 | H13: =[1]spy!F11/[1]spy!F12-1 -> 0.020043926
A14: 45261 | B14: 455.77 | C14: 477.55 | D14: 454.31 | E14: 475.31 | F14: 468.97 | G14: 1643108100 | H14: =[1]spy!F12/[1]spy!F13-1 -> 0.04143812
... A61: 43831 | B61: 323.54 | C61: 332.95 | D61: 320.36 | E61: 321.73 | F61: 299.29 | G61: 1392003800 | H61: =[1]spy!F59/[1]spy!F60-1 -> 0.0045311136
A62: 43800 | B62: 314.59 | C62: 323.8 | D62: 307.13 | E62: 321.86 | F62: 297.94 | G62: 1285175800

Sheet Sheet4
A1: Date
A3: 45597 | B3: =UNH!H3 -> 0.049123118 | C3: =SPY!H3 -> 0.01417417 | G3: =SLOPE(B3:B61,C3:C61) -> 0.57680352 | O3: Equity beta (β) = 0.5768
A4: 45566 | B4: =UNH!H4 -> -0.031084259 | C4: =SPY!H4 -> -0.0058915054 | O4: Corporate tax rate = 21% or 0.21
A5: 45536 | B5: =UNH!H5 -> -0.009351992 | C5: =SPY!H5 -> 0.017883835 | O5: Market value of debt (D) = $62,637
A6: 45505 | B6: =UNH!H6 -> 0.024367728 | C6: =SPY!H6 -> 0.023364231 | O6: Market value of equity (E) = $88,756
A7: 45474 | B7: =UNH!H7 -> 0.13615135 | C7: =SPY!H7 -> 0.015384331
A8: 45444 | B8: =UNH!H8 -> 0.028055256 | C8: =SPY!H8 -> 0.031942298 | O8: Asset Beta = Equity Beta / [1 + (1 - Tax Rate) * Debt/Equity Ratio]
A9: 45413 | B9: =UNH!H9 -> 0.024127513 | C9: =SPY!H9 -> 0.050577339
A10: 45383 | B10: =UNH!H10 -> -0.018386714 | C10: =SPY!H10 -> -0.037322938 | O10: =0.3714 -> 0.3714
A11: 45352 | B11: =UNH!H11 -> 0.0022342933 | C11: =SPY!H11 -> 0.029503507
A12: 45323 | B12: =UNH!H12 -> -0.035450196 | C12: =SPY!H12 -> 0.052177185
A13: 45292 | B13: =UNH!H13 -> -0.02466398 | C13: =SPY!H13 -> 0.020043926
A14: 45261 | B14: =UNH!H14 -> -0.047936403 | C14: =SPY!H14 -> 0.04143812
A15: 45231 | B15: =UNH!H15 -> 0.032509999 | C15: =SPY!H15 -> 0.091343124
A16: 45200 | B16: =UNH!H16 -> 0.066363453 | C16: =SPY!H16 -> -0.018249304
A17: 45170 | B17: =UNH!H17 -> 0.057932893 | C17: =SPY!H17 -> -0.050792719
A18: 45139 | B18: =UNH!H18 -> -0.058831817 | C18: =SPY!H18 -> -0.016241196
A19: 45108 | B19: =UNH!H19 -> 0.057849128 | C19: =SPY!H19 -> 0.036548293
A20: 45078 | B20: =UNH!H20 -> -0.013547005 | C20: =SPY!H20 -> 0.060858518
A21: 45047 | B21: =UNH!H21 -> -0.0098573389 | C21: =SPY!H21 -> 0.0046389475
A22: 45017 | B22: =UNH!H22 -> 0.044984353 | C22: =SPY!H22 -> 0.019850309
... A61: 43831 | B61: =UNH!H61 -> -0.06966868 | C61: =SPY!H61 -> 0.0045311136
A62: 43800

Sheet Proforma income statement
E1: Pro-forma income statement
A2: US$ in millions | E2: US$ in millions
A3: 12 months ended: | B3: 45291 | C3: Percenatge of sales | E3: 12 months ended: | F3: 45657 | G3: 46022 | H3: 46387
A4: Premiums | B4: 290827 | C4: =B4/B7 -> 0.79129493 | E4: Premiums | F4: =C4*$F$7 -> 328634.51 | G4: =C4*$G$7 -> 371357 | H4: =C4*$H$7 -> 419633.41
A5: Products | B5: 42583 | C5: =B5/B7 -> 0.1158617 | E5: Products | F5: =C5*$F$7 -> 48118.79 | G5: =C5*$G$7 -> 54374.233 | H5: =C5*$H$7 -> 61442.883
A6: Services | B6: 34123 | C6: =B6/B7 -> 0.092843364 | E6: Services | F6: =C6*$F$7 -> 38558.99 | G6: =C6*$G$7 -> 43571.659 | H6: =C6*$H$7 -> 49235.974
A7: Revenues, customers | B7: 367533 | C7: =B7/B7 -> 1 | E7: Revenues, customers | F7: =B7*113% -> 415312.29 | G7: =F7*113% -> 469302.89 | H7: =G7*113% -> 530312.26
A8: Medical costs | B8: -241894 | C8: =B8/B7 -> -0.65815587 | E8: Medical costs | F8: =C8*$F$7 -> -273340.22 | G8: =C8*$G$7 -> -308874.45 | H8: =C8*$H$7 -> -349028.13
A9: Cost of products sold | B9: -38770 | C9: =B9/$B$7 -> -0.10548713 | E9: Cost of products sold | F9: =C9*$F$7 -> -43810.1 | G9: =C9*$G$7 -> -49505.413 | H9: =C9*$H$7 -> -55941.117
A10: Cost of revenues | B10: -280664 | C10: =B10/$B$7 -> -0.76364299 | E10: Cost of revenues | F10: =C10*$F$7 -> -317150.32 | G10: =C10*$G$7 -> -358379.86 | H10: =C10*$H$7 -> -404969.24
A11: Gross profit | B11: 86869 | C11: =B11/$B$7 -> 0.23635701 | E11: Gross profit | F11: =C11*$F$7 -> 98161.97 | G11: =C11*$G$7 -> 110923.03 | H11: =C11*$H$7 -> 125343.02
A12: Investment and other income | B12: 4089 | C12: =B12/$B$7 -> 0.011125532 | E12: Investment and other income | F12: =C12*$F$7 -> 4620.57 | G12: =C12*$G$7 -> 5221.2441 | H12: =C12*$H$7 -> 5900.0058
A13: Operating costs | B13: -54628 | C13: =B13/$B$7 -> -0.14863427 | E13: Operating costs | F13: =C13*$F$7 -> -61729.64 | G13: =C13*$G$7 -> -69754.493 | H13: =C13*$H$7 -> -78822.577
A14: Depreciation and amortization | B14: -3972 | C14: =B14/$B$7 -> -0.010807193 | E14: Depreciation and amortization | F14: =C14*$F$7 -> -4488.36 | G14: =C14*$G$7 -> -5071.8468 | H14: =C14*$H$7 -> -5731.1869
A15: Earnings from operations | B15: 32358 | C15: =B15/$B$7 -> 0.088041074 | E15: Earnings from operations | F15: =C15*$F$7 -> 36564.54 | G15: =C15*$G$7 -> 41317.93 | H15: =C15*$H$7 -> 46689.261
A16: Interest expense | B16: -3246 | C16: =B16/$B$7 -> -0.00883186 | E16: Interest expense | F16: =C16*$F$7 -> -3667.98 | G16: =C16*$G$7 -> -4144.8174 | H16: =C16*$H$7 -> -4683.6437
A17: Earnings before income taxes | B17: 29112 | C17: =B17/$B$7 -> 0.079209214 | E17: Earnings before income taxes | F17: =C17*$F$7 -> 32896.56 | G17: =C17*$G$7 -> 37173.113 | H17: =C17*$H$7 -> 42005.617
A18: Provision for income taxes | B18: -5968 | C18: =B18/$B$7 -> -0.016237998 | E18: Provision for income taxes | F18: =C18*$F$7 -> -6743.84 | G18: =C18*$G$7 -> -7620.5392 | H18: =C18*$H$7 -> -8611.2093
A19: Net earnings | B19: 23144 | C19: =B19/$B$7 -> 0.062971216 | E19: Net earnings | F19: =C19*$F$7 -> 26152.72 | G19: =C19*$G$7 -> 29552.574 | H19: =C19*$H$7 -> 33394.408
A20: Earnings attributable to noncontrolling interests | B20: -763 | C20: =B20/$B$7 -> -0.0020760041 | E20: Earnings attributable to noncontrolling interests | F20: =C20*$F$7 -> -862.19 | G20: =C20*$G$7 -> -974.2747 | H20: =C20*$H$7 -> -1100.9304
A21: Net earnings attributable to UnitedHealth Group common shareholders | B21: 22381 | C21: =B21/$B$7 -> 0.060895212 | E21: Net earnings attributable to UnitedHealth Group common shareholders | F21: =C21*$F$7 -> 25290.53 | G21: =C21*$G$7 -> 28578.299 | H21: =C21*$H$7 -> 32293.478
E24: Sales growth rate = 13%, based on average of previous 3 years sales growth rate…..
